tensorflow_model_analysis/__init__.py
tensorflow_model_analysis/constants.py
tensorflow_model_analysis/sdk.py
tensorflow_model_analysis/version.py
tensorflow_model_analysis/api/__init__.py
tensorflow_model_analysis/api/dataframe.py
tensorflow_model_analysis/api/dataframe_test.py
tensorflow_model_analysis/api/model_eval_lib.py
tensorflow_model_analysis/api/model_eval_lib_test.py
tensorflow_model_analysis/api/types.py
tensorflow_model_analysis/api/types_test.py
tensorflow_model_analysis/api/verifier_lib.py
tensorflow_model_analysis/contrib/__init__.py
tensorflow_model_analysis/contrib/aggregates/__init__.py
tensorflow_model_analysis/contrib/aggregates/binary_confusion_matrices.py
tensorflow_model_analysis/contrib/aggregates/binary_confusion_matrices_test.py
tensorflow_model_analysis/eval_metrics_graph/__init__.py
tensorflow_model_analysis/eval_metrics_graph/eval_metrics_graph.py
tensorflow_model_analysis/eval_saved_model/__init__.py
tensorflow_model_analysis/eval_saved_model/constants.py
tensorflow_model_analysis/evaluators/__init__.py
tensorflow_model_analysis/evaluators/analysis_table_evaluator.py
tensorflow_model_analysis/evaluators/analysis_table_evaluator_test.py
tensorflow_model_analysis/evaluators/confidence_intervals_util.py
tensorflow_model_analysis/evaluators/confidence_intervals_util_test.py
tensorflow_model_analysis/evaluators/counter_util.py
tensorflow_model_analysis/evaluators/counter_util_test.py
tensorflow_model_analysis/evaluators/evaluator.py
tensorflow_model_analysis/evaluators/evaluator_test.py
tensorflow_model_analysis/evaluators/jackknife.py
tensorflow_model_analysis/evaluators/jackknife_test.py
tensorflow_model_analysis/evaluators/keras_util.py
tensorflow_model_analysis/evaluators/legacy_poisson_bootstrap.py
tensorflow_model_analysis/evaluators/legacy_poisson_bootstrap_test.py
tensorflow_model_analysis/evaluators/metrics_plots_and_validations_evaluator.py
tensorflow_model_analysis/evaluators/metrics_plots_and_validations_evaluator_test.py
tensorflow_model_analysis-0.48.0.dist-info/licenses/LICENSE
tensorflow_model_analysis-0.48.0.dist-info/METADATA
tensorflow_model_analysis-0.48.0.dist-info/WHEEL
tensorflow_model_analysis-0.48.0.dist-info/namespace_packages.txt
tensorflow_model_analysis-0.48.0.dist-info/top_level.txt
tensorflow_model_analysis-0.48.0.dist-info/RECORD
